Metadata-Version: 2.1
Name: trl-fpo
Version: 0.0.15
Summary: Train transformer language models with reinforcement learning.
Home-page: https://github.com/huggingface/trl
Author: Rajarshi, Gurpreet, Danush
Author-email: royrajarshi0123@gmail.com
License: Apache 2.0
Keywords: ppo,transformers,huggingface,gpt2,language modeling,rlhf
Classifier: Development Status :: 2 - Pre-Alpha
Classifier: Intended Audience :: Developers
Classifier: Intended Audience :: Science/Research
Classifier: License :: OSI Approved :: Apache Software License
Classifier: Natural Language :: English
Classifier: Operating System :: OS Independent
Classifier: Programming Language :: Python :: 3
Classifier: Programming Language :: Python :: 3.7
Classifier: Programming Language :: Python :: 3.8
Classifier: Programming Language :: Python :: 3.9
Classifier: Programming Language :: Python :: 3.10
Requires-Python: >=3.7
License-File: LICENSE
Requires-Dist: torch (>=1.4.0)
Requires-Dist: transformers (>=4.31.0)
Requires-Dist: numpy (<2.0.0,>=1.18.2)
Requires-Dist: accelerate
Requires-Dist: datasets
Requires-Dist: tyro (>=0.5.11)
Requires-Dist: peft
Requires-Dist: wandb
Requires-Dist: deepspeed
Requires-Dist: stanza
Requires-Dist: nltk
Requires-Dist: scipy
Provides-Extra: benchmark
Requires-Dist: wandb ; extra == 'benchmark'
Requires-Dist: ghapi ; extra == 'benchmark'
Requires-Dist: openrlbenchmark (==0.2.1a5) ; extra == 'benchmark'
Requires-Dist: requests ; extra == 'benchmark'
Requires-Dist: deepspeed ; extra == 'benchmark'
Provides-Extra: deepspeed
Requires-Dist: deepspeed (>=0.9.5) ; extra == 'deepspeed'
Provides-Extra: dev
Requires-Dist: parameterized ; extra == 'dev'
Requires-Dist: peft (>=0.8.0) ; extra == 'dev'
Requires-Dist: pytest ; extra == 'dev'
Requires-Dist: pytest-xdist ; extra == 'dev'
Requires-Dist: pytest-cov ; extra == 'dev'
Requires-Dist: scikit-learn ; extra == 'dev'
Requires-Dist: Pillow ; extra == 'dev'
Requires-Dist: diffusers (>=0.18.0) ; extra == 'dev'
Requires-Dist: deepspeed (>=0.9.5) ; extra == 'dev'
Requires-Dist: wandb ; extra == 'dev'
Requires-Dist: ghapi ; extra == 'dev'
Requires-Dist: openrlbenchmark (==0.2.1a5) ; extra == 'dev'
Requires-Dist: requests ; extra == 'dev'
Requires-Dist: deepspeed ; extra == 'dev'
Requires-Dist: bitsandbytes (<=0.41.1) ; extra == 'dev'
Requires-Dist: openai (>=1.23.2) ; extra == 'dev'
Requires-Dist: huggingface-hub (>=0.22.2) ; extra == 'dev'
Requires-Dist: llm-blender (>=0.0.2) ; extra == 'dev'
Provides-Extra: diffusers
Requires-Dist: diffusers (>=0.18.0) ; extra == 'diffusers'
Provides-Extra: llm_judge
Requires-Dist: openai (>=1.23.2) ; extra == 'llm_judge'
Requires-Dist: huggingface-hub (>=0.22.2) ; extra == 'llm_judge'
Requires-Dist: llm-blender (>=0.0.2) ; extra == 'llm_judge'
Provides-Extra: peft
Requires-Dist: peft (>=0.8.0) ; extra == 'peft'
Provides-Extra: quantization
Requires-Dist: bitsandbytes (<=0.41.1) ; extra == 'quantization'
Provides-Extra: test
Requires-Dist: parameterized ; extra == 'test'
Requires-Dist: peft (>=0.8.0) ; extra == 'test'
Requires-Dist: pytest ; extra == 'test'
Requires-Dist: pytest-xdist ; extra == 'test'
Requires-Dist: pytest-cov ; extra == 'test'
Requires-Dist: scikit-learn ; extra == 'test'
Requires-Dist: Pillow ; extra == 'test'
